halwa.py
setup.py
Halwa.egg-info/PKG-INFO
Halwa.egg-info/SOURCES.txt
Halwa.egg-info/dependency_links.txt
Halwa.egg-info/requires.txt
Halwa.egg-info/top_level.txt
Halwa.egg-info/zip-safe