Metadata-Version: 1.1
Name: Halwa
Version: 0.1.3
Summary: Single file static site generator.
Home-page: https://github.com/mhlakhani/halwa
Author: Hasnain Lakhani
Author-email: m.hasnain.lakhani@gmail.com
License: UNKNOWN
Download-URL: git+https://github.com/mhlakhani/halwa.git
Keywords: static site generator
Platform: UNKNOWN
